pycpu_rainbow/__init__.py
tests/__init__.py
tests/test_pycpu_rainbow.py
PyCPU_RAINBOW-0.42.0.dist-info/LICENSE
PyCPU_RAINBOW-0.42.0.dist-info/METADATA
PyCPU_RAINBOW-0.42.0.dist-info/WHEEL
PyCPU_RAINBOW-0.42.0.dist-info/top_level.txt
PyCPU_RAINBOW-0.42.0.dist-info/RECORD
