Metadata-Version: 2.1
Name: PyCPU-RAINBOW
Version: 0.42.0
Summary: A PyCPU for https://rainbow4th.readme.io
Home-page: https://github.com/scott91e1/RAINBOW4TH
Author: Scott McCallum (https github.com scott91e1)
Author-email: 262464@195387.com
License: UNKNOWN
Platform: UNKNOWN
Classifier: Programming Language :: Python :: 3
Classifier: License :: OSI Approved :: MIT License
Classifier: Operating System :: OS Independent
Requires-Python: >=3.6
